LICENSE.txt
MANIFEST.in
README.md
setup.py
pylods/__init__.py
pylods/decorators.py
pylods/deserialize.py
pylods/dict.py
pylods/error.py
pylods/mapper.py
pylods/serialize.py
pylods.egg-info/PKG-INFO
pylods.egg-info/SOURCES.txt
pylods.egg-info/dependency_links.txt
pylods.egg-info/requires.txt
pylods.egg-info/top_level.txt
pylods/backend/__init__.py
pylods/backend/pylodsc/__init__.py
pylods/backend/pylodsc/mapper.py
pylods/backend/pylodsp/__init__.py
pylods/backend/pylodsp/mapper.py
pylodsc/include/Dictionary.h
pylodsc/include/PyDictionary.h
pylodsc/include/pylodsc.h
pylodsc/include/pylodscapi.h
pylodsc/src/Dictionary.cpp
pylodsc/src/PyDictionary.cpp
pylodsc/src/pylodsc.cpp
pylodsc/src/pylodscapi.cpp