Metadata-Version: 1.1
Name: pylods
Version: 0.4.4
Summary: Pylods, is a python library for object deserialization and serialization. Pylods provides tools to allow automatic recursive serialization of class instances and implementation of customizes rs and deserializers similar to JacksonJson for java. It currently supports JSON and Msgpack
Home-page: https://github.com/salimm/pylods
Author: Salim Malakouti
Author-email: salim.malakouti@gmail.com
License: MIT
Download-URL: http://github.com/salimm/pylods/archive/0.4.4.tar.gz
Keywords: python,serialization,deserialization,paser,json,msgpack,object oriented,fast,extendable,type based,jackson json
Platform: UNKNOWN
Classifier: Programming Language :: Python
